README.md
setup.py
seven_dyapp/__init__.py
seven_dyapp.egg-info/PKG-INFO
seven_dyapp.egg-info/SOURCES.txt
seven_dyapp.egg-info/dependency_links.txt
seven_dyapp.egg-info/requires.txt
seven_dyapp.egg-info/top_level.txt
seven_dyapp/handlers/__init__.py
seven_dyapp/handlers/base/__init__.py
seven_dyapp/handlers/base/behavior_base.py
seven_dyapp/handlers/base/client_base.py
seven_dyapp/handlers/base/douyin_base.py
seven_dyapp/handlers/base/douyin_pay_base.py
seven_dyapp/handlers/base/seven_helper.py
seven_dyapp/models/__init__.py
seven_dyapp/models/seven_model.py
seven_dyapp/models/db_models/__init__.py
seven_dyapp/models/db_models/behavior/__init__.py
seven_dyapp/models/db_models/behavior/behavior_log_model.py
seven_dyapp/models/db_models/behavior/behavior_orm_model.py
seven_dyapp/models/db_models/behavior/behavior_report_model.py